jupyterhealth_client/__init__.py
jupyterhealth_client/_client.py
jupyterhealth_client/_utils.py
jupyterhealth_client-0.0.1a4.dist-info/METADATA
jupyterhealth_client-0.0.1a4.dist-info/WHEEL
jupyterhealth_client-0.0.1a4.dist-info/licenses/LICENSE
jupyterhealth_client-0.0.1a4.dist-info/RECORD
