Metadata-Version: 2.4
Name: jupyterhealth-client
Version: 0.0.1a4
Summary: JupyterHealth client library
Project-URL: Documentation, https://jupyterhealth-client.readthedocs.org
Project-URL: Issues, https://github.com/jupyterhealth/jupyterhealth-client/issues
Project-URL: Source, https://github.com/jupyterhealth/jupyterhealth-client
Author-email: Jupyter <benjaminrk@gmail.com>
License: BSD 3-Clause License
License-File: LICENSE
Classifier: Development Status :: 3 - Alpha
Classifier: Framework :: Jupyter
Classifier: Operating System :: OS Independent
Classifier: Programming Language :: Python :: 3
Requires-Python: >=3.9
Requires-Dist: pandas
Requires-Dist: requests
Requires-Dist: yarl
Provides-Extra: test
Requires-Dist: pytest; extra == 'test'
